{
	"credit": "Made with Blockbench",
	"parent": "minecraft:block/block",
	"textures": {
		"particle": "forgedingears:item/uncooked/uncooked_faucet",
		"tex": "forgedingears:item/uncooked/uncooked_faucet"
	},
	"elements": [
		{
			"name": "The bottom platform, facing south with the dark texture side",
			"from": [4, 4, 10],
			"to": [12, 6, 16],
			"faces": {
				"north": {"uv": [4, 9, 12, 11], "texture": "#tex"},
				"east": {"uv": [12, 10, 14, 16], "rotation": 90, "texture": "#tex"},
				"south": {"uv": [4, 11, 12, 9], "texture": "#tex", "cullface": "south"},
				"west": {"uv": [2, 10, 4, 16], "rotation": 270, "texture": "#tex"},
				"up": {"uv": [4, 10, 12, 16], "texture": "#tex"},
				"down": {"uv": [4, 10, 12, 16], "rotation": 180, "texture": "#tex"}
			}
		},
		{
			"name": "Left side from front (east)",
			"from": [10, 6, 10],
			"to": [12, 10, 16],
			"faces": {
				"north": {"uv": [4, 9, 6, 5], "texture": "#tex"},
				"east": {"uv": [8, 10, 12, 16], "rotation": 90, "texture": "#tex"},
				"south": {"uv": [10, 9, 12, 5], "texture": "#tex", "cullface": "south"},
				"west": {"uv": [2, 10, 6, 16], "rotation": 270, "texture": "#tex"},
				"up": {"uv": [13, 10, 15, 16], "texture": "#tex"}
			}
		},
		{
			"name": "Right side from front (west)",
			"from": [4, 6, 10],
			"to": [6, 10, 16],
			"faces": {
				"north": {"uv": [10, 9, 12, 5], "texture": "#tex"},
				"east": {"uv": [2, 10, 6, 16], "rotation": 90, "texture": "#tex"},
				"south": {"uv": [6, 9, 4, 5], "texture": "#tex", "cullface": "south"},
				"west": {"uv": [7, 10, 11, 16], "rotation": 270, "texture": "#tex"},
				"up": {"uv": [1, 10, 3, 16], "texture": "#tex"}
			}
		}
	],
	"display": {
		"thirdperson_righthand": {
			"rotation": [75, 45, 0],
			"translation": [0, 3, 0.5],
			"scale": [0.4, 0.4, 0.4]
		},
		"thirdperson_lefthand": {
			"rotation": [75, 45, 0],
			"translation": [0, 3, 0.5],
			"scale": [0.4, 0.4, 0.4]
		},
		"firstperson_righthand": {
			"rotation": [0, 135, 0],
			"translation": [0, 0.5, 0],
			"scale": [0.5, 0.5, 0.5]
		},
		"firstperson_lefthand": {
			"rotation": [0, 135, 0],
			"translation": [0, 0.5, 0],
			"scale": [0.5, 0.5, 0.5]
		},
		"ground": {
			"translation": [0, 3, -1],
			"scale": [0.25, 0.25, 0.25]
		},
		"gui": {
			"rotation": [30, 225, 0],
			"translation": [3, -1, 0],
			"scale": [0.9375, 0.9375, 0.9375]
		},
		"fixed": {
			"translation": [0, 0, -1],
			"scale": [0.5, 0.5, 0.5]
		}
	}
}